MANIFEST.in
README.txt
setup.py
docs/HISTORY.txt
docs/INSTALL.txt
docs/LICENSE.GPL
docs/LICENSE.txt
rer/__init__.py
rer.structured_content.egg-info/PKG-INFO
rer.structured_content.egg-info/SOURCES.txt
rer.structured_content.egg-info/dependency_links.txt
rer.structured_content.egg-info/entry_points.txt
rer.structured_content.egg-info/namespace_packages.txt
rer.structured_content.egg-info/not-zip-safe
rer.structured_content.egg-info/requires.txt
rer.structured_content.egg-info/top_level.txt
rer/structured_content/README.txt
rer/structured_content/__init__.py
rer/structured_content/config.py
rer/structured_content/configure.zcml
rer/structured_content/i18n.sh
rer/structured_content/setuphandlers.py
rer/structured_content/browser/__init__.py
rer/structured_content/browser/configure.zcml
rer/structured_content/browser/context.py
rer/structured_content/browser/folder_deep.gif
rer/structured_content/browser/folder_struct.gif
rer/structured_content/browser/structured_content.css
rer/structured_content/browser/structured_document_view.pt
rer/structured_content/browser/structured_document_view.py
rer/structured_content/content/__init__.py
rer/structured_content/content/configure.zcml
rer/structured_content/content/folderdeepening.py
rer/structured_content/content/structureddocument.py
rer/structured_content/i18n/plone-it.po
rer/structured_content/i18n/plone.pot
rer/structured_content/interfaces/__init__.py
rer/structured_content/interfaces/folderdeepening.py
rer/structured_content/interfaces/structureddocument.py
rer/structured_content/interfaces/structuredinterface.py
rer/structured_content/locales/rer.structured_content.pot
rer/structured_content/locales/it/LC_MESSAGES/rer.structured_content.mo
rer/structured_content/locales/it/LC_MESSAGES/rer.structured_content.po
rer/structured_content/profiles/default/cssregistry.xml
rer/structured_content/profiles/default/diff_tool.xml
rer/structured_content/profiles/default/factorytool.xml
rer/structured_content/profiles/default/metadata.xml
rer/structured_content/profiles/default/propertiestool.xml
rer/structured_content/profiles/default/repositorytool.xml
rer/structured_content/profiles/default/rer.structured_content_various.txt
rer/structured_content/profiles/default/rolemap.xml
rer/structured_content/profiles/default/tinymce.xml
rer/structured_content/profiles/default/types.xml
