Metadata-Version: 1.1
Name: rer.structured-content
Version: 1.8.3
Summary: A simple folderish page content for Plone
Home-page: http://plone.org/products/rer.structured_content
Author: RedTurtle Technology
Author-email: sviluppoplone@redturtle.net
License: GPL
Keywords: plonegov content structured document
Platform: UNKNOWN
Classifier: Framework :: Plone
Classifier: Programming Language :: Python
Classifier: Intended Audience :: Developers
Classifier: License :: OSI Approved :: GNU General Public License (GPL)
Classifier: Development Status :: 4 - Beta
